faceghost/__init__.py
faceghost/blur.py
faceghost/pipeline.py
faceghost/yolo_infer.py
faceghost/model/v0-1.onnx
faceghost-0.1.5.dist-info/licenses/LICENSE
faceghost-0.1.5.dist-info/METADATA
faceghost-0.1.5.dist-info/WHEEL
faceghost-0.1.5.dist-info/entry_points.txt
faceghost-0.1.5.dist-info/top_level.txt
faceghost-0.1.5.dist-info/RECORD
