Metadata-Version: 2.4
Name: faceghost
Version: 0.1.5
Summary: Face anonymization utilities (blur faces in images & video)
Home-page: https://github.com/ayusrjn/face-anonymization
Author: Ayush Ranjan
Author-email: ayushraanjan@gmail.com
License: MIT
Classifier: Programming Language :: Python :: 3
Classifier: Programming Language :: Python :: 3.8
Classifier: License :: OSI Approved :: MIT License
Classifier: Operating System :: OS Independent
Requires-Python: >=3.8
License-File: LICENSE
Requires-Dist: opencv-python-headless
Requires-Dist: tqdm
Requires-Dist: numpy
Requires-Dist: onnxruntime
Dynamic: license-file
